LICENSE
MANIFEST.in
README.rst
setup.cfg
setup.py
django_formwizard_deprecated.egg-info/PKG-INFO
django_formwizard_deprecated.egg-info/SOURCES.txt
django_formwizard_deprecated.egg-info/dependency_links.txt
django_formwizard_deprecated.egg-info/top_level.txt
formwizard_deprecated/__init__.py
formwizard_deprecated/legacy.py