Metadata-Version: 1.1
Name: django-formwizard-deprecated
Version: 0.0.1
Summary: Original django.contrib.formtools.legacy.FormWizard from Django 1.5.12
Home-page: https://github.com/fcurella/django-formwizard-deprecated
Author: Flavio Curella
Author-email: flavio.curella@gmail.com
License: BSD
Platform: UNKNOWN
Classifier: Development Status :: 7 - Inactive
Classifier: Environment :: Web Environment
Classifier: Framework :: Django
Classifier: Intended Audience :: Developers
Classifier: License :: OSI Approved :: BSD License
Classifier: Operating System :: OS Independent
Classifier: Programming Language :: Python
